{
  "routes":
  [
    {
      "name": "Bremerhaven-Hamburg",
      "agents":
      [
        {
          "minLong": 0,
          "maxLong": 10,
          "predictors":
          [
            {
              "modelPath": "resources/m5pTree.model",
              "classAttribute": "RemainingTravelTimeInMinutes"
            }
          ]
        }
      ]
    },
    {
      "name": "Kiel-Gdynia",
      "agents":
      [
        {
          "minLong": 10.1,
          "maxLong": 20,
          "predictors":
          [
            {
              "modelPath": "resources/M5P.model",
              "classAttribute": "RemainingTravelTimeInMinutes"
            }
          ]
        }
      ]
    }
  ]
}
